[
    { "id": 1, "word": "nopal" },
    { "id": 2, "word": "tacos" },
    { "id": 3, "word": "chile" },
    { "id": 4, "word": "guaje" },
    { "id": 5, "word": "jarro" },
    { "id": 6, "word": "moles" },
    { "id": 7, "word": "pozol" },
    { "id": 8, "word": "tamal" },
    { "id": 9, "word": "cacao" },
    { "id": 10, "word": "chido" },
    { "id": 11, "word": "fresa" },
    { "id": 12, "word": "chela" },
    { "id": 13, "word": "cuate" },
    { "id": 14, "word": "torta" },
    { "id": 15, "word": "queso" },
    { "id": 16, "word": "chafa" },
    { "id": 17, "word": "vatos" },
    { "id": 18, "word": "pisto" },
    { "id": 19, "word": "gordo" },
    { "id": 20, "word": "chavo" },
    { "id": 21, "word": "banda" },
    { "id": 22, "word": "guero" },
    { "id": 23, "word": "ocote" },
    { "id": 24, "word": "joven" },
    { "id": 25, "word": "mague" },
    { "id": 26, "word": "tripa" },
    { "id": 27, "word": "santo" },
    { "id": 28, "word": "clavo" },
    { "id": 29, "word": "mixto" },
    { "id": 30, "word": "gacho" },
    { "id": 31, "word": "botas" },
    { "id": 32, "word": "quila" },
    { "id": 33, "word": "miada" },
    { "id": 34, "word": "amigo" },
    { "id": 35, "word": "burro" },
    { "id": 36, "word": "perro" },
    { "id": 37, "word": "calle" },
    { "id": 38, "word": "baile" },
    { "id": 39, "word": "jalar" },
    { "id": 40, "word": "feria" },
    { "id": 41, "word": "blusa" },
    { "id": 42, "word": "chano" },
    { "id": 43, "word": "canoa" },
    { "id": 44, "word": "avena" },
    { "id": 45, "word": "quema" },
    { "id": 46, "word": "elote" },
    { "id": 47, "word": "caldo" },
    { "id": 48, "word": "jaina" },
    { "id": 49, "word": "papas" },
    { "id": 50, "word": "pluma" },
    { "id": 51, "word": "nieve" },
    { "id": 52, "word": "chato" },
    { "id": 53, "word": "enano" },
    { "id": 54, "word": "parra" },
    { "id": 55, "word": "queso" },
    { "id": 56, "word": "tamal" },
    { "id": 57, "word": "rogar" },
    { "id": 58, "word": "plomo" },
    { "id": 59, "word": "musgo" },
    { "id": 60, "word": "frase" },
    { "id": 61, "word": "gorro" },
    { "id": 62, "word": "tarro" },
    { "id": 63, "word": "tarde" },
    { "id": 64, "word": "lunes" },
    { "id": 65, "word": "pasta" },
    { "id": 66, "word": "brisa" },
    { "id": 67, "word": "verde" },
    { "id": 68, "word": "cuate" },
    { "id": 69, "word": "mango" },
    { "id": 70, "word": "negro" },
    { "id": 71, "word": "carro" },
    { "id": 72, "word": "manso" },
    { "id": 73, "word": "tarea" },
    { "id": 74, "word": "verde" }
]
